oarepo_enrollment_permissions/__init__.py
oarepo_enrollment_permissions/config.py
oarepo_enrollment_permissions/ext.py
oarepo_enrollment_permissions/permissions.py
oarepo_enrollment_permissions/proxies.py
oarepo_enrollment_permissions/search.py
oarepo_enrollment_permissions/version.py
oarepo_enrollment_permissions/handlers/__init__.py
oarepo_enrollment_permissions/handlers/collection.py
oarepo_enrollment_permissions/handlers/record.py
tests/__init__.py
tests/conftest.py
tests/helpers.py
tests/search.py
tests/test_rest_create.py
tests/test_rest_delete.py
tests/test_rest_get.py
tests/test_rest_list.py
tests/test_rest_update.py
tests/mappings/__init__.py
tests/mappings/v7/__init__.py
oarepo_enrollment_permissions-1.0.1.dist-info/LICENSE
oarepo_enrollment_permissions-1.0.1.dist-info/METADATA
oarepo_enrollment_permissions-1.0.1.dist-info/WHEEL
oarepo_enrollment_permissions-1.0.1.dist-info/entry_points.txt
oarepo_enrollment_permissions-1.0.1.dist-info/top_level.txt
oarepo_enrollment_permissions-1.0.1.dist-info/RECORD
