Metadata-Version: 2.1
Name: oarepo-enrollment-permissions
Version: 1.0.1
Summary: OArepo Enrollment library for record metadata validation
Home-page: https://github.com/oarepo/oarepo-enrollment-permissions
Author: UCT Prague
Author-email: miroslav.simek@vscht.cz
License: MIT
Keywords: invenio oarepo user enrollment
Platform: any
Classifier: Environment :: Web Environment
Classifier: Intended Audience :: Developers
Classifier: License :: OSI Approved :: MIT License
Classifier: Operating System :: OS Independent
Classifier: Programming Language :: Python
Classifier: Topic :: Internet :: WWW/HTTP :: Dynamic Content
Classifier: Topic :: Software Development :: Libraries :: Python Modules
Classifier: Programming Language :: Python :: 3
Classifier: Programming Language :: Python :: 3.8
Classifier: Development Status :: 4 - Beta
Requires-Dist: wrapt (>=1.11.2)
Requires-Dist: oarepo-enrollments
Provides-Extra: dev
Requires-Dist: pytest ; extra == 'dev'
Requires-Dist: oarepo[tests] (~=3.3) ; extra == 'dev'
Requires-Dist: markdown-toc ; extra == 'dev'
Provides-Extra: tests
Requires-Dist: pytest ; extra == 'tests'
Requires-Dist: oarepo[tests] (~=3.3) ; extra == 'tests'
